game_coro-0.0.1.dist-info/METADATA
game_coro-0.0.1.dist-info/WHEEL
game_coro-0.0.1.dist-info/licenses/LICENSE
game_coro/__init__.py
game_coro/context.py
game_coro/coroutine.py
game_coro/manager.py
game_coro/misc.py
game_coro-0.0.1.dist-info/RECORD
