Metadata-Version: 2.1
Name: game-coro
Version: 0.0.1
Summary: Coroutine runner for games
Home-page: https://github.com/cspotcode/py_game_coroutines
Author-Email: Andrew Bradley <cspotcode@gmail.com>
License: MIT
Project-URL: Homepage, https://github.com/cspotcode/py_game_coroutines
Requires-Python: >=3.10
Provides-Extra: dev
Requires-Dist: arcade>=2.6.17; extra == "dev"
